facevision
