Metadata-Version: 1.1
Name: facevision
Version: 0.0.4
Summary: The computer vision library focused on facial recognition pipeline.
Home-page: UNKNOWN
Author: Felipe Oliveira
Author-email: gavb@gavb.com
License: UNKNOWN
Platform: UNKNOWN
Classifier: Programming Language :: Python :: 3
Classifier: License :: OSI Approved :: MIT License
Classifier: Operating System :: OS Independent
